vlite2/__init__.py
vlite2/ingestors.py
vlite2/main.py
vlite2/model.py
vlite2/utils.py
vlite2-3.5.0.dist-info/LICENSE
vlite2-3.5.0.dist-info/METADATA
vlite2-3.5.0.dist-info/WHEEL
vlite2-3.5.0.dist-info/top_level.txt
vlite2-3.5.0.dist-info/RECORD
