Metadata-Version: 2.1
Name: vlite2
Version: 3.5.0
Summary: Improved simple vector database, with many advanced proprietary features. Original VLite by @sdan.
Home-page: https://github.com/raydelvecchio/vlite-v2
Author: Ray Del Vecchio
Author-email: ray@cerebralvalley.ai
License-File: LICENSE
Requires-Dist: numpy
Requires-Dist: Requests
Requires-Dist: setuptools
Requires-Dist: torch
Requires-Dist: transformers
Requires-Dist: uuid
Requires-Dist: usearch
Requires-Dist: PyPDF2
Requires-Dist: docx2txt
